test/__init__.py
test/test_functions.py
text_toolkit/__init__.py
text_toolkit/cleaner.py
text_toolkit/logger.py
text_toolkit/slicer.py
text_toolkit/splitter.py
text_slicer-0.1.0.dist-info/METADATA
text_slicer-0.1.0.dist-info/WHEEL
text_slicer-0.1.0.dist-info/top_level.txt
text_slicer-0.1.0.dist-info/RECORD
