Metadata-Version: 2.1
Name: text-slicer
Version: 0.1.0
Summary: A toolkit for text cleaning, splitting, and slicing.
Author: David Zhang
Author-email: digitalboyzone@gmail.com
Requires-Dist: beautifulsoup4
Requires-Dist: regex
